most/__init__.py
most/_constrants.py
most/api.py
most/async_api.py
most/async_badge.py
most/async_catalog.py
most/async_glossary.py
most/async_searcher.py
most/async_teleprompter.py
most/async_trainer_api.py
most/badge.py
most/catalog.py
most/glossary.py
most/score_calculation.py
most/search_types.py
most/searcher.py
most/teleprompter.py
most/trainer_api.py
most/types.py
most/utils.py
most/admin/__init__.py
most/admin/async_tuner.py
most/admin/tuner.py
most_client-1.0.80.dist-info/METADATA
most_client-1.0.80.dist-info/WHEEL
most_client-1.0.80.dist-info/top_level.txt
most_client-1.0.80.dist-info/zip-safe
most_client-1.0.80.dist-info/RECORD
