Metadata-Version: 2.4
Name: most-client
Version: 1.0.80
Summary: Most AI API for https://the-most.ai
Home-page: https://github.com/the-most-ai/most-client
Author: George Kasparyants
Author-email: george@the-most.ai
Classifier: Intended Audience :: Developers
Classifier: Operating System :: OS Independent
Classifier: Topic :: Software Development :: Libraries :: Python Modules
Classifier: Programming Language :: Python
Classifier: Programming Language :: Python :: 3 :: Only
Classifier: Programming Language :: Python :: 3.6
Requires-Python: >=3.6
Requires-Dist: requests
Requires-Dist: wheel
Requires-Dist: adaptix
Requires-Dist: json5
Requires-Dist: dataclasses_json
Requires-Dist: black
Requires-Dist: coverage
Requires-Dist: flake8
Requires-Dist: mypy
Requires-Dist: pylint
Requires-Dist: pytest
Requires-Dist: tox
Requires-Dist: twine
Requires-Dist: httpx
Requires-Dist: pydub
Requires-Dist: aiofiles
Dynamic: author
Dynamic: author-email
Dynamic: classifier
Dynamic: home-page
Dynamic: requires-dist
Dynamic: requires-python
Dynamic: summary
